fastarray/__init__.py
fastarray/indicies.py
fastarray/io.py
fastarray/tensor.py
fastarray/transform.py
fastarray-0.1.1.dist-info/licenses/LICENSE
fastarray-0.1.1.dist-info/METADATA
fastarray-0.1.1.dist-info/WHEEL
fastarray-0.1.1.dist-info/top_level.txt
fastarray-0.1.1.dist-info/RECORD
