Metadata-Version: 2.4
Name: FastArray
Version: 0.1.1
Summary: A lightweight Python package for preprocessing geospatial optical imagery for machine learning
Author-email: "Isah Abdul-Azeez." <isahabdul16@gmail.com>
License: MIT
Requires-Python: >=3.8
License-File: LICENSE
Requires-Dist: numpy
Requires-Dist: xarray
Requires-Dist: aiofiles
Requires-Dist: matplotlib
Requires-Dist: torch
Requires-Dist: rioxarray
Requires-Dist: pyproj
Requires-Dist: shapely
Dynamic: license-file
